sufarray/__init__.py
sufarray/py.typed
sufarray_kkto-0.1.1.dist-info/LICENSE
sufarray_kkto-0.1.1.dist-info/METADATA
sufarray_kkto-0.1.1.dist-info/WHEEL
sufarray_kkto-0.1.1.dist-info/top_level.txt
sufarray_kkto-0.1.1.dist-info/RECORD
