Metadata-Version: 2.1
Name: sufarray-kkto
Version: 0.1.1
Summary: Suffix Array for all-substring search
Home-page: https://github.com/isaacto/sufarray
Author: Isaac To
Author-email: isaac.to@gmail.com
License: UNKNOWN
Platform: UNKNOWN
Classifier: Development Status :: 4 - Beta
Classifier: Programming Language :: Python :: 3.5
Classifier: Programming Language :: Python :: 3.6
Classifier: Programming Language :: Python :: 3.7
Classifier: Programming Language :: Python :: 3.8
Classifier: Topic :: Software Development :: Libraries
Classifier: License :: OSI Approved :: MIT License
Classifier: Operating System :: OS Independent
Requires-Python: ~=3.5
